<?xml version="1.0" encoding="utf-8"?>
<!DOCTYPE hibernate-mapping PUBLIC "-//Hibernate/Hibernate Mapping DTD 3.0//EN"
"http://www.hibernate.org/dtd/hibernate-mapping-3.0.dtd">
<!-- 
    Mapping file autogenerated by MyEclipse Persistence Tools
-->
<hibernate-mapping>
    <class name="mydb.Singer" table="singer" catalog="musicfm">
        <id name="singerid" type="java.lang.Integer">
            <column name="singerid" />
            <generator class="increment" />
        </id>
        <property name="singername" type="java.lang.String">
            <column name="singername" length="45" not-null="true" />
        </property>
        <property name="singersex" type="java.lang.String">
            <column name="singersex" length="1" />
        </property>
        <property name="singerimage" type="java.lang.String">
            <column name="singerimage" length="300" />
        </property>
        <property name="singerdescription" type="java.lang.String">
            <column name="singerdescription" length="65535" />
        </property>
    </class>
</hibernate-mapping>
